README.rst
setup.py
jingen/__init__.py
jingen/jingen.py
jingen/manual_tester.py
jingen.egg-info/PKG-INFO
jingen.egg-info/SOURCES.txt
jingen.egg-info/dependency_links.txt
jingen.egg-info/requires.txt
jingen.egg-info/top_level.txt